CONTRIBUTING.rst
HISTORY.rst
LICENSE
MANIFEST.in
README.rst
setup.cfg
setup.py
docs/Makefile
docs/conf.py
docs/contributing.rst
docs/history.rst
docs/index.rst
docs/installation.rst
docs/make.bat
docs/readme.rst
docs/usage.rst
tests/__init__.py
tests/test_yaml_patcher.py
yaml_patcher/__init__.py
yaml_patcher/cli.py
yaml_patcher/yaml_patcher.py
yaml_patcher.egg-info/PKG-INFO
yaml_patcher.egg-info/SOURCES.txt
yaml_patcher.egg-info/dependency_links.txt
yaml_patcher.egg-info/entry_points.txt
yaml_patcher.egg-info/not-zip-safe
yaml_patcher.egg-info/requires.txt
yaml_patcher.egg-info/top_level.txt