Metadata-Version: 1.2
Name: yaml-patcher
Version: 0.1.0
Summary: Patch yaml files.
Home-page: https://github.com/albertoeaf/yaml_patcher
Author: Alberto Ferreira
Author-email: albertoeaf@users.noreply.github.com
License: Apache Software License 2.0
Keywords: yaml_patcher
Platform: UNKNOWN
Classifier: Development Status :: 2 - Pre-Alpha
Classifier: Intended Audience :: Developers
Classifier: License :: OSI Approved :: Apache Software License
Classifier: Natural Language :: English
Classifier: Programming Language :: Python :: 3
Classifier: Programming Language :: Python :: 3.5
Classifier: Programming Language :: Python :: 3.6
Classifier: Programming Language :: Python :: 3.7
Classifier: Programming Language :: Python :: 3.8
Requires-Python: >=3.5
